ldsnotes/__init__.py
ldsnotes/annotations.py
ldsnotes/content.py
ldsnotes/note.py
ldsnotes-0.1.5.dist-info/LICENSE
ldsnotes-0.1.5.dist-info/METADATA
ldsnotes-0.1.5.dist-info/WHEEL
ldsnotes-0.1.5.dist-info/top_level.txt
ldsnotes-0.1.5.dist-info/RECORD
