Metadata-Version: 2.1
Name: ldsnotes
Version: 0.1.5
Summary: Unofficial Python API to read your annotations from lds.org
Home-page: https://github.com/contagon/ldsnotes
Author: Easton Potokar
Author-email: contagon6@gmail.com
License: MIT license
Keywords: ldsnotes
Platform: UNKNOWN
Classifier: Development Status :: 2 - Pre-Alpha
Classifier: Intended Audience :: Developers
Classifier: License :: OSI Approved :: MIT License
Classifier: Natural Language :: English
Classifier: Programming Language :: Python :: 3
Classifier: Programming Language :: Python :: 3.7
Classifier: Programming Language :: Python :: 3.8
Classifier: Programming Language :: Python :: 3.9
Requires-Python: >=3.7
Requires-Dist: chromedriver-autoinstaller (==0.2.2)
Requires-Dist: selenium (==3.141.0)
Requires-Dist: requests (==2.25.1)
Requires-Dist: addict (==2.4.0)
Requires-Dist: datetime (==4.3)
